<?xml version="1.0" encoding="UTF-8"?><item typename="Article" product="TyndaleOpenBibleDictionary" name="BethAven">
  <title>Beth-Aven</title>
  <body>
<p class="h1">BETH-AVEN</p>
<p class="list">1. Town in Benjamin’s territory, located west of Michmash on the border of the wilderness, near Ai, to the east of Bethel (<a href="?bref=Josh.7.2">Jos 7:2</a>; <a href="?bref=Josh.18.12">18:12</a>; <a href="?bref=1Sam.13.5">1 Sm 13:5</a>; <a href="?bref=1Sam.14.23">14:23</a>).</p>
<p class="list">2. Term used by Hosea contemptuously to refer to Bethel, an ancient center of worship, because the “House of God” (Bethel) had become a “house of wickedness” (Beth-aven or just Aven; <a href="?bref=Hos.4.15">Hos 4:15</a>; <a href="?bref=Hos.5.8">5:8</a>; <a href="?bref=Hos.10.5">10:5</a>). <span class="ital">See</span> <a href="?item=Aven_Article_TyndaleOpenBibleDictionary">Aven #2</a>.</p>
  </body>
</item>