<?xml version="1.0" encoding="UTF-8"?><item typename="Article" product="TyndaleOpenBibleDictionary" name="Ahlai">
  <title>Ahlai</title>
  <body>
<p class="h1">AHLAI</p>
<p class="list">1. Sheshan’s daughter, a member of Judah’s tribe (<a href="?bref=1Chr.2.31,34">1 Chr 2:31, 34</a>). In verse <a href="?bref=1Chr.2.31">31</a> some translations refer to Ahlai as a son.</p>
<p class="list">2. Zabad’s father or ancestor. Zabad was one of David’s mighty men who were known as “the thirty” (<a href="?bref=1Chr.11.41">1 Chr 11:41</a>).</p>
  </body>
</item>