<?xml version="1.0" encoding="UTF-8"?><item typename="Article" product="TyndaleOpenBibleDictionary" name="LevirateMarriage">
  <title>Levirate Marriage*</title>
  <body>
<p class="h1">LEVIRATE MARRIAGE*</p>
<p class="fl">Israelite custom in which a man, upon the death of his brother, marries his brother’s widow and raises up children for his brother. <span class="ital">See</span> <a href="?item=MarriageMarriageCustoms_Article_TyndaleOpenBibleDictionary">Marriage, Marriage Customs</a>.</p>
  </body>
</item>