<?xml version="1.0" encoding="UTF-8"?><item typename="Article" product="TyndaleOpenBibleDictionary" name="Salathiel">
  <title>Salathiel*</title>
  <body>
<p class="h1">SALATHIEL*</p>
<p class="fl">KJV alternate spelling of Shealtiel, King Jehoiachin’s son, in <a href="?bref=1Chr.3.17">1 Chronicles 3:17</a>, <a href="?bref=Matt.1.12">Matthew 1:12</a>, and <a href="?bref=Luke.3.27">Luke 3:27</a>. <span class="ital">See</span> <a href="?item=Shealtiel_Article_TyndaleOpenBibleDictionary">Shealtiel</a>.</p>
  </body>
</item>