<?xml version="1.0" encoding="UTF-8"?><item typename="Article" product="TyndaleOpenBibleDictionary" name="Shelah">
  <title>Shelah</title>
  <body>
<p class="h1">SHELAH</p>
<p class="list">1. Arphaxad’s son and the father of Eber (<a href="?bref=Gen.10.24">Gn 10:24</a>; <a href="?bref=Gen.11.12-15">11:12-15</a>; <a href="?bref=1Chr.1.18">1 Chr 1:18</a>). Shelah is listed in Luke’s genealogy of Christ as the son of Cainan the son of Arphaxad (<a href="?bref=Luke.3.35">Lk 3:35</a>). <span class="ital">See</span> <a href="?item=GenealogyofJesusChrist_Article_TyndaleOpenBibleDictionary">Genealogy of Jesus Christ</a>.</p>
<p class="list">2. Judah’s third son by Bathshua the Canaanitess. He was born at Kezib, a small town in Judah (<a href="?bref=Gen.38.5">Gn 38:5</a>; <a href="?bref=1Chr.2.3">1 Chr 2:3</a>). Shelah founded the Shelanite family (<a href="?bref=Num.26.20">Nm 26:20</a>), which should possibly be read instead of “Shilonite” in <a href="?bref=Neh.11.5">Nehemiah 11:5</a>; <a href="?bref=1Chr.9.5">1 Chronicles 9:5</a>.</p>
  </body>
</item>