<?xml version="1.0" encoding="UTF-8"?><item typename="Article" product="TyndaleOpenBibleDictionary" name="Firkin">
  <title>Firkin*</title>
  <body>
<p class="h1">FIRKIN*</p>
<p class="fl">Measure of about 10 gallons (37.9 liters). In <a href="?bref=John.2.6">John 2:6</a>, firkin is the <span class="sc">kjv</span> translation for the name of a Greek liquid measure. <span class="ital">See</span> <a href="?item=WeightsandMeasures_Article_TyndaleOpenBibleDictionary">Weights and Measures</a>.</p>
  </body>
</item>