<?xml version="1.0" encoding="UTF-8"?><item typename="Article" product="TyndaleOpenBibleDictionary" name="Heber">
  <title>Heber</title>
  <body>
<p class="h1">HEBER</p>
<p class="list">1. Descendant of Jacob through Asher and Beriah (<a href="?bref=Gen.46.17">Gn 46:17</a>) and father of the family of Heberites (<a href="?bref=Num.26.45">Nm 26:45</a>; <a href="?bref=1Chr.7.31-32">1 Chr 7:31-32</a>).</p>
<p class="list">2. Husband of Jael, the woman who deceptively killed Sisera, known as Heber the Kenite (<a href="?bref=Judg.4.11-21">Jgs 4:11-21</a>; <a href="?bref=Judg.5.24">5:24</a>).</p>
<p class="list">3. Judahite, Mered’s son and the father of Soco (<a href="?bref=1Chr.4.18">1 Chr 4:18</a>).</p>
<p class="list">4. Elpaal’s son from Judah’s tribe (<a href="?bref=1Chr.8.17">1 Chr 8:17</a>).</p>
<p class="list">5. KJV spelling for Eber in <a href="?bref=1Chr.5.13">1 Chronicles 5:13</a>; <a href="?bref=1Chr.8.22">8:22</a>; and <a href="?bref=Luke.3.35">Luke 3:35</a>. <span class="ital">See</span> <a href="?item=Eber_Article_TyndaleOpenBibleDictionary">Eber #1, #2, #4</a>.</p>
  </body>
</item>