<?xml version="1.0" encoding="UTF-8"?><item typename="Article" product="TyndaleOpenBibleDictionary" name="WesternText">
  <title>Western Text*</title>
  <body>
<p class="h1">WESTERN TEXT*</p>
<p class="fl">According to the classification of B. F. Wescott and F. J. A. Hort, one of the four principal text types of the Greek New Testament. <span class="ital">See</span> <a href="?item=BibleManuscriptsandTextoftheNewTestament_Article_TyndaleOpenBibleDictionary">Bible, Manuscripts and Text of the (New Testament)</a>.</p>
  </body>
</item>